2_SIM/4_SAMPLE/pipeline.v
`timescale 1ns / 1ps

module pipeline(
	clk	,
	rst_n	,
	in1	,
	in2	,
	in3	,	
	out
);

	input clk;
	input rst_n;
	input [9:0] in1;
	input [9:0] in2;
	input [9:0] in3;
	output [11:0] out;

	reg [10:0] temp_add1;
	always @(posedge clk, negedge rst_n)
	begin
	   if (~rst_n) temp_add1 <=11'b0;
	   else	       temp_add1 <= {1'b0, in1} + {1'b0, in2};
	end

	reg [9:0] temp_in3;
	always @(posedge clk, negedge rst_n)
	begin
	   if (~rst_n) temp_in3 <= 10'b0;
	   else       temp_in3 <= in3;
        end

	reg [11:0] out;
	always @(posedge clk, negedge rst_n)
	begin
	   if (~rst_n) out <= 12'b0;
	   else        out <= {1'b0, temp_add1} + {2'b0, temp_in3};
        end



endmodule

2_SIM/4_SAMPLE/tb_pipeline.v
`timescale 1ns / 1ps

	
	module tb_pipeline ();

	reg 		clk, rst_n;
	reg [9:0]	in1;
	reg [9:0]	in2;
	reg [9:0]	in3;
	wire[11:0]	piped_out;


	always #5 clk = ~clk;

	initial begin
	clk 	= 1'b0;
	rst_n	= 1'b0;
	in1 	= 10'd0;
	in2	= 10'd0;
	in3	= 10'd0;

	#10
	rst_n = 1'b1;

	#20
	in1 = 10'd1; in2 = 10'd2; in3 = 10'd3;

	#30
	in1 = 10'd4; in2 = 10'd5; in3 = 10'd6;

	#40
	in1 = 10'd7; in2 = 10'd8; in3 = 10'd9;

	#50
	rst_n = 1'b0;

	#100
	$finish;

end


	pipeline uut (
	.clk	(clk		),	
	.rst_n	(rst_n		),
	.in1	(in1		),
	.in2	(in2		),
	.in3	(in3		),
	.out	(piped_out	)
);

initial begin
	$dumpfile("./pipeline.vcd");
	$dumpvars(0, uut);

end

endmodule

2_SIM/4_SAMPLE/pipeline.vcd
$date
    Jun 30, 2026  22:39:36
$end
$version
    TOOL:	xmsim(64)	22.03-s012
$end
$timescale
    1 ps
$end

$scope module tb_pipeline $end

$scope module uut $end
$var wire      1 !    clk  $end
$var wire      1 "    rst_n  $end
$var wire     10 #    in1 [9:0] $end
$var wire     10 $    in2 [9:0] $end
$var wire     10 %    in3 [9:0] $end
$var reg      12 &    out [11:0] $end
$var reg      11 '    temp_add1 [10:0] $end
$var reg      10 (    temp_in3 [9:0] $end
$upscope $end

$upscope $end

$enddefinitions $end
$dumpvars
0!
0"
b0 #
b0 $
b0 %
b0 &
b0 '
b0 (
$end
#5000
1!
#10000
0!
1"
#15000
1!
#20000
0!
#25000
1!
#30000
0!
b11 %
b10 $
b1 #
#35000
1!
b11 (
b11 '
#40000
0!
#45000
1!
b110 &
#50000
0!
#55000
1!
#60000
0!
b110 %
b101 $
b100 #
#65000
1!
b110 (
b1001 '
#70000
0!
#75000
1!
b1111 &
#80000
0!
#85000
1!
#90000
0!
#95000
1!
#100000
0!
b1001 %
b1000 $
b111 #
#105000
1!
b1001 (
b1111 '
#110000
0!
#115000
1!
b11000 &
#120000
0!
#125000
1!
#130000
0!
#135000
1!
#140000
0!
#145000
1!
#150000
0!
0"
b0 (
b0 '
b0 &
